dbmt/__init__.py
dbmt/config.py
dbmt/database_plugin.py
dbmt/dataclasses.py
dbmt/error.py
dbmt/main.py
dbmt/mysql.py
plugins/__init__.py
plugins/mysql.py
plugins/sqlite.py
db_migration_tool-0.1.1.dist-info/LICENSE.txt
db_migration_tool-0.1.1.dist-info/METADATA
db_migration_tool-0.1.1.dist-info/WHEEL
db_migration_tool-0.1.1.dist-info/entry_points.txt
db_migration_tool-0.1.1.dist-info/top_level.txt
db_migration_tool-0.1.1.dist-info/RECORD
