Metadata-Version: 2.1
Name: db-migration-tool
Version: 0.1.1
Summary: A command line utility
Author: Fredrik Haglund
Author-email: fr3h4g@gmail.com
Classifier: Programming Language :: Python :: 3
Classifier: Programming Language :: Python :: 3.7
Classifier: Programming Language :: Python :: 3.8
Classifier: Programming Language :: Python :: 3.9
Classifier: Programming Language :: Python :: 3.10
Classifier: License :: OSI Approved :: MIT License
Classifier: Operating System :: OS Independent
Requires-Python: >=3.7
License-File: LICENSE.txt
Requires-Dist: click
Requires-Dist: invoke
Requires-Dist: rich
Requires-Dist: PyInquirer
Requires-Dist: pyyaml
Requires-Dist: python-dotenv
Requires-Dist: pyfiglet
Requires-Dist: sqlparse
Requires-Dist: mysql-connector-python
